{
  "$schema": "http://cyclonedx.org/schema/bom-1.4.schema.json",
  "bomFormat": "CycloneDX",
  "specVersion": "1.4",
  "serialNumber": "urn:uuid:728175fe-7cdf-4751-9319-7d4bc36cfe55",
  "version": 1,
  "metadata": {
    "timestamp": "2022-12-29T13:06:50.160213+00:00",
    "tools": [
      {
        "vendor": "CycloneDX",
        "name": "cyclonedx-bom",
        "version": "3.10.1"
      },
      {
        "vendor": "CycloneDX",
        "name": "cyclonedx-python-lib",
        "version": "3.1.1",
        "externalReferences": [
          {
            "url": "https://github.com/CycloneDX/cyclonedx-python-lib/actions",
            "type": "build-system"
          },
          {
            "url": "https://pypi.org/project/cyclonedx-python-lib/",
            "type": "distribution"
          },
          {
            "url": "https://cyclonedx.github.io/cyclonedx-python-lib/",
            "type": "documentation"
          },
          {
            "url": "https://github.com/CycloneDX/cyclonedx-python-lib/issues",
            "type": "issue-tracker"
          },
          {
            "url": "https://github.com/CycloneDX/cyclonedx-python-lib/blob/main/LICENSE",
            "type": "license"
          },
          {
            "url": "https://github.com/CycloneDX/cyclonedx-python-lib/blob/main/CHANGELOG.md",
            "type": "release-notes"
          },
          {
            "url": "https://github.com/CycloneDX/cyclonedx-python-lib",
            "type": "vcs"
          },
          {
            "url": "https://cyclonedx.org",
            "type": "website"
          }
        ]
      }
    ]
  },
  "components": [
    {
      "type": "library",
      "bom-ref": "bc1efcf2-5e64-4ef4-9abe-c7cb8b387292",
      "name": "jmespath",
      "version": "1.0.1",
      "purl": "pkg:pypi/jmespath@1.0.1"
    },
    {
      "type": "library",
      "bom-ref": "0e20c524-03e3-491d-95db-5487576774cd",
      "name": "jsonschema",
      "version": "4.17.3",
      "purl": "pkg:pypi/jsonschema@4.17.3"
    },
    {
      "type": "library",
      "bom-ref": "c66a77c1-6758-4285-9820-afa7081718ee",
      "name": "langcodes",
      "version": "3.3.0",
      "purl": "pkg:pypi/langcodes@3.3.0"
    },
    {
      "type": "library",
      "bom-ref": "ef972dce-8fac-4eb8-9b1b-75b4a138c6b6",
      "name": "lazr.uri",
      "version": "1.0.6",
      "purl": "pkg:pypi/lazr.uri@1.0.6"
    },
    {
      "type": "library",
      "bom-ref": "0e1e8191-b146-47e0-b00f-a571a4577115",
      "name": "msgspec",
      "version": "0.11.0",
      "purl": "pkg:pypi/msgspec@0.11.0"
    },
    {
      "type": "library",
      "bom-ref": "cf880d56-35c9-4a42-84de-c581d65b4ba2",
      "name": "pydantic",
      "version": "1.10.3",
      "purl": "pkg:pypi/pydantic@1.10.3"
    },
    {
      "type": "library",
      "bom-ref": "9f3d2b17-3042-4523-aaed-05d382cfb768",
      "name": "scooby",
      "version": "0.7.0",
      "purl": "pkg:pypi/scooby@0.7.0"
    },
    {
      "type": "library",
      "bom-ref": "3f18c1cc-5cc3-4dda-b9b5-8b216c9a0e6c",
      "name": "setuptools",
      "version": "65.6.3",
      "purl": "pkg:pypi/setuptools@65.6.3"
    },
    {
      "type": "library",
      "bom-ref": "6eab53db-27cc-41b1-b8e9-7f3b63b138b0",
      "name": "typer",
      "version": "0.7.0",
      "purl": "pkg:pypi/typer@0.7.0"
    }
  ],
  "dependencies": [
    {
      "ref": "bc1efcf2-5e64-4ef4-9abe-c7cb8b387292",
      "dependsOn": []
    },
    {
      "ref": "0e20c524-03e3-491d-95db-5487576774cd",
      "dependsOn": []
    },
    {
      "ref": "c66a77c1-6758-4285-9820-afa7081718ee",
      "dependsOn": []
    },
    {
      "ref": "ef972dce-8fac-4eb8-9b1b-75b4a138c6b6",
      "dependsOn": []
    },
    {
      "ref": "0e1e8191-b146-47e0-b00f-a571a4577115",
      "dependsOn": []
    },
    {
      "ref": "cf880d56-35c9-4a42-84de-c581d65b4ba2",
      "dependsOn": []
    },
    {
      "ref": "9f3d2b17-3042-4523-aaed-05d382cfb768",
      "dependsOn": []
    },
    {
      "ref": "3f18c1cc-5cc3-4dda-b9b5-8b216c9a0e6c",
      "dependsOn": []
    },
    {
      "ref": "6eab53db-27cc-41b1-b8e9-7f3b63b138b0",
      "dependsOn": []
    }
  ]
}
