{
  "SPDXID" : "SPDXRef-DOCUMENT",
  "spdxVersion" : "SPDX-2.3",
  "creationInfo" : {
    "comment" : "Converted from CycloneDX spec version 1.4",
    "created" : "2023-09-25T18:06:25Z",
    "creators" : [ "Tool: CycloneDX:cyclonedx-bom-3.11.2", "Tool: CycloneDX:cyclonedx-python-lib-3.1.5", "Tool: CycloneToSpdx-0.1.4" ],
    "licenseListVersion" : "3.21"
  },
  "name" : "From-Cyclone-DX",
  "dataLicense" : "CC0-1.0",
  "annotations" : [ {
    "annotationDate" : "2023-09-25T18:06:26Z",
    "annotationType" : "OTHER",
    "annotator" : "Tool: CycloneToSpdx",
    "comment" : "MISSING_CDX_PROPERTY:extensions={}"
  } ],
  "documentNamespace" : "https://cyclonedx/063ffa88-425f-4a34-9e41-5bbbde042672_1",
  "packages" : [ {
    "SPDXID" : "SPDXRef-5a813eee-ce25-478b-bc47-b6118edc55f6",
    "annotations" : [ {
      "annotationDate" : "2023-09-25T18:06:26Z",
      "annotationType" : "OTHER",
      "annotator" : "Tool: CycloneToSpdx",
      "comment" : "MISSING_CDX_PROPERTY:componentType=\"LIBRARY\""
    } ],
    "copyrightText" : "NOASSERTION",
    "downloadLocation" : "NOASSERTION",
    "externalRefs" : [ {
      "referenceCategory" : "PACKAGE-MANAGER",
      "referenceLocator" : "pkg:pypi/jmespath@1.0.1",
      "referenceType" : "purl"
    } ],
    "filesAnalyzed" : false,
    "licenseConcluded" : "NOASSERTION",
    "licenseDeclared" : "NOASSERTION",
    "name" : "jmespath",
    "primaryPackagePurpose" : "LIBRARY",
    "versionInfo" : "1.0.1"
  }, {
    "SPDXID" : "SPDXRef-cdfdbb7f-35a9-4375-bd4b-5cd8f56a1c47",
    "annotations" : [ {
      "annotationDate" : "2023-09-25T18:06:26Z",
      "annotationType" : "OTHER",
      "annotator" : "Tool: CycloneToSpdx",
      "comment" : "MISSING_CDX_PROPERTY:componentType=\"LIBRARY\""
    } ],
    "copyrightText" : "NOASSERTION",
    "downloadLocation" : "NOASSERTION",
    "externalRefs" : [ {
      "referenceCategory" : "PACKAGE-MANAGER",
      "referenceLocator" : "pkg:pypi/typer@0.9.0",
      "referenceType" : "purl"
    } ],
    "filesAnalyzed" : false,
    "licenseConcluded" : "NOASSERTION",
    "licenseDeclared" : "NOASSERTION",
    "name" : "typer",
    "primaryPackagePurpose" : "LIBRARY",
    "versionInfo" : "0.9.0"
  }, {
    "SPDXID" : "SPDXRef-fcecbb57-07f6-4e4f-8808-baa65e9be1a7",
    "annotations" : [ {
      "annotationDate" : "2023-09-25T18:06:26Z",
      "annotationType" : "OTHER",
      "annotator" : "Tool: CycloneToSpdx",
      "comment" : "MISSING_CDX_PROPERTY:componentType=\"LIBRARY\""
    } ],
    "copyrightText" : "NOASSERTION",
    "downloadLocation" : "NOASSERTION",
    "externalRefs" : [ {
      "referenceCategory" : "PACKAGE-MANAGER",
      "referenceLocator" : "pkg:pypi/lazr.uri@1.0.6",
      "referenceType" : "purl"
    } ],
    "filesAnalyzed" : false,
    "licenseConcluded" : "NOASSERTION",
    "licenseDeclared" : "NOASSERTION",
    "name" : "lazr.uri",
    "primaryPackagePurpose" : "LIBRARY",
    "versionInfo" : "1.0.6"
  }, {
    "SPDXID" : "SPDXRef-c5b34942-a4c3-40cc-9e78-da926013456b",
    "annotations" : [ {
      "annotationDate" : "2023-09-25T18:06:26Z",
      "annotationType" : "OTHER",
      "annotator" : "Tool: CycloneToSpdx",
      "comment" : "MISSING_CDX_PROPERTY:componentType=\"LIBRARY\""
    } ],
    "copyrightText" : "NOASSERTION",
    "downloadLocation" : "NOASSERTION",
    "externalRefs" : [ {
      "referenceCategory" : "PACKAGE-MANAGER",
      "referenceLocator" : "pkg:pypi/scooby@0.7.3",
      "referenceType" : "purl"
    } ],
    "filesAnalyzed" : false,
    "licenseConcluded" : "NOASSERTION",
    "licenseDeclared" : "NOASSERTION",
    "name" : "scooby",
    "primaryPackagePurpose" : "LIBRARY",
    "versionInfo" : "0.7.3"
  }, {
    "SPDXID" : "SPDXRef-c1567dc5-a4bd-4a76-9e63-b06a6b937c9c",
    "annotations" : [ {
      "annotationDate" : "2023-09-25T18:06:26Z",
      "annotationType" : "OTHER",
      "annotator" : "Tool: CycloneToSpdx",
      "comment" : "MISSING_CDX_PROPERTY:componentType=\"LIBRARY\""
    } ],
    "copyrightText" : "NOASSERTION",
    "downloadLocation" : "NOASSERTION",
    "externalRefs" : [ {
      "referenceCategory" : "PACKAGE-MANAGER",
      "referenceLocator" : "pkg:pypi/msgspec@0.18.2",
      "referenceType" : "purl"
    } ],
    "filesAnalyzed" : false,
    "licenseConcluded" : "NOASSERTION",
    "licenseDeclared" : "NOASSERTION",
    "name" : "msgspec",
    "primaryPackagePurpose" : "LIBRARY",
    "versionInfo" : "0.18.2"
  }, {
    "SPDXID" : "SPDXRef-123c8494-4fdf-4c79-83c9-7239aa1228fc",
    "annotations" : [ {
      "annotationDate" : "2023-09-25T18:06:26Z",
      "annotationType" : "OTHER",
      "annotator" : "Tool: CycloneToSpdx",
      "comment" : "MISSING_CDX_PROPERTY:componentType=\"LIBRARY\""
    } ],
    "copyrightText" : "NOASSERTION",
    "downloadLocation" : "NOASSERTION",
    "externalRefs" : [ {
      "referenceCategory" : "PACKAGE-MANAGER",
      "referenceLocator" : "pkg:pypi/langcodes@3.3.0",
      "referenceType" : "purl"
    } ],
    "filesAnalyzed" : false,
    "licenseConcluded" : "NOASSERTION",
    "licenseDeclared" : "NOASSERTION",
    "name" : "langcodes",
    "primaryPackagePurpose" : "LIBRARY",
    "versionInfo" : "3.3.0"
  }, {
    "SPDXID" : "SPDXRef-18e08ac5-27c6-4f01-aebd-ed6da686d8de",
    "annotations" : [ {
      "annotationDate" : "2023-09-25T18:06:26Z",
      "annotationType" : "OTHER",
      "annotator" : "Tool: CycloneToSpdx",
      "comment" : "MISSING_CDX_PROPERTY:componentType=\"LIBRARY\""
    } ],
    "copyrightText" : "NOASSERTION",
    "downloadLocation" : "NOASSERTION",
    "externalRefs" : [ {
      "referenceCategory" : "PACKAGE-MANAGER",
      "referenceLocator" : "pkg:pypi/referencing@0.30.2",
      "referenceType" : "purl"
    } ],
    "filesAnalyzed" : false,
    "licenseConcluded" : "NOASSERTION",
    "licenseDeclared" : "NOASSERTION",
    "name" : "referencing",
    "primaryPackagePurpose" : "LIBRARY",
    "versionInfo" : "0.30.2"
  }, {
    "SPDXID" : "SPDXRef-93e929bd-c238-4640-ad31-801f86d21e5b",
    "annotations" : [ {
      "annotationDate" : "2023-09-25T18:06:26Z",
      "annotationType" : "OTHER",
      "annotator" : "Tool: CycloneToSpdx",
      "comment" : "MISSING_CDX_PROPERTY:componentType=\"LIBRARY\""
    } ],
    "copyrightText" : "NOASSERTION",
    "downloadLocation" : "NOASSERTION",
    "externalRefs" : [ {
      "referenceCategory" : "PACKAGE-MANAGER",
      "referenceLocator" : "pkg:pypi/pydantic@2.4.0",
      "referenceType" : "purl"
    } ],
    "filesAnalyzed" : false,
    "licenseConcluded" : "NOASSERTION",
    "licenseDeclared" : "NOASSERTION",
    "name" : "pydantic",
    "primaryPackagePurpose" : "LIBRARY",
    "versionInfo" : "2.4.0"
  }, {
    "SPDXID" : "SPDXRef-ca44b728-d83b-40e7-987f-9d25a3519f8e",
    "annotations" : [ {
      "annotationDate" : "2023-09-25T18:06:26Z",
      "annotationType" : "OTHER",
      "annotator" : "Tool: CycloneToSpdx",
      "comment" : "MISSING_CDX_PROPERTY:componentType=\"LIBRARY\""
    } ],
    "copyrightText" : "NOASSERTION",
    "downloadLocation" : "NOASSERTION",
    "externalRefs" : [ {
      "referenceCategory" : "PACKAGE-MANAGER",
      "referenceLocator" : "pkg:pypi/setuptools@68.2.2",
      "referenceType" : "purl"
    } ],
    "filesAnalyzed" : false,
    "licenseConcluded" : "NOASSERTION",
    "licenseDeclared" : "NOASSERTION",
    "name" : "setuptools",
    "primaryPackagePurpose" : "LIBRARY",
    "versionInfo" : "68.2.2"
  }, {
    "SPDXID" : "SPDXRef-5c49647e-6d25-4074-84cb-8f7921abeffe",
    "annotations" : [ {
      "annotationDate" : "2023-09-25T18:06:26Z",
      "annotationType" : "OTHER",
      "annotator" : "Tool: CycloneToSpdx",
      "comment" : "MISSING_CDX_PROPERTY:componentType=\"LIBRARY\""
    } ],
    "copyrightText" : "NOASSERTION",
    "downloadLocation" : "NOASSERTION",
    "externalRefs" : [ {
      "referenceCategory" : "PACKAGE-MANAGER",
      "referenceLocator" : "pkg:pypi/jsonschema@4.19.1",
      "referenceType" : "purl"
    } ],
    "filesAnalyzed" : false,
    "licenseConcluded" : "NOASSERTION",
    "licenseDeclared" : "NOASSERTION",
    "name" : "jsonschema",
    "primaryPackagePurpose" : "LIBRARY",
    "versionInfo" : "4.19.1"
  } ],
  "relationships" : [ {
    "spdxElementId" : "SPDXRef-DOCUMENT",
    "relationshipType" : "DESCRIBES",
    "relatedSpdxElement" : "SPDXRef-93e929bd-c238-4640-ad31-801f86d21e5b"
  }, {
    "spdxElementId" : "SPDXRef-DOCUMENT",
    "relationshipType" : "DESCRIBES",
    "relatedSpdxElement" : "SPDXRef-c1567dc5-a4bd-4a76-9e63-b06a6b937c9c"
  }, {
    "spdxElementId" : "SPDXRef-DOCUMENT",
    "relationshipType" : "DESCRIBES",
    "relatedSpdxElement" : "SPDXRef-5c49647e-6d25-4074-84cb-8f7921abeffe"
  }, {
    "spdxElementId" : "SPDXRef-DOCUMENT",
    "relationshipType" : "DESCRIBES",
    "relatedSpdxElement" : "SPDXRef-5a813eee-ce25-478b-bc47-b6118edc55f6"
  }, {
    "spdxElementId" : "SPDXRef-DOCUMENT",
    "relationshipType" : "DESCRIBES",
    "relatedSpdxElement" : "SPDXRef-fcecbb57-07f6-4e4f-8808-baa65e9be1a7"
  }, {
    "spdxElementId" : "SPDXRef-DOCUMENT",
    "relationshipType" : "DESCRIBES",
    "relatedSpdxElement" : "SPDXRef-123c8494-4fdf-4c79-83c9-7239aa1228fc"
  }, {
    "spdxElementId" : "SPDXRef-DOCUMENT",
    "relationshipType" : "DESCRIBES",
    "relatedSpdxElement" : "SPDXRef-ca44b728-d83b-40e7-987f-9d25a3519f8e"
  }, {
    "spdxElementId" : "SPDXRef-DOCUMENT",
    "relationshipType" : "DESCRIBES",
    "relatedSpdxElement" : "SPDXRef-c5b34942-a4c3-40cc-9e78-da926013456b"
  }, {
    "spdxElementId" : "SPDXRef-DOCUMENT",
    "relationshipType" : "DESCRIBES",
    "relatedSpdxElement" : "SPDXRef-cdfdbb7f-35a9-4375-bd4b-5cd8f56a1c47"
  }, {
    "spdxElementId" : "SPDXRef-DOCUMENT",
    "relationshipType" : "DESCRIBES",
    "relatedSpdxElement" : "SPDXRef-18e08ac5-27c6-4f01-aebd-ed6da686d8de"
  } ]
}